mccann_hub/odoolib/__init__.py
mccann_hub/odoolib/dates.py
mccann_hub/odoolib/main.py
mccann_hub/odoolib/model.py
mccann_hub/odoolib/service.py
mccann_hub/odoolib/connection/__init__.py
mccann_hub/odoolib/connection/_connection.py
mccann_hub/odoolib/connection/_servicer.py
mccann_hub/odoolib/connection/authentication_error.py
mccann_hub/odoolib/connector/__init__.py
mccann_hub/odoolib/connector/_connector.py
mccann_hub/odoolib/connector/_sender.py
mccann_hub/odoolib/connector/json_rpc.py
mccann_hub/odoolib/connector/json_rpcs.py
mccann_hub/odoolib/connector/xml_rpc.py
mccann_hub/odoolib/connector/xml_rpcs.py
mccann_hub_odoo_client_lib-2.0.2.dist-info/METADATA
mccann_hub_odoo_client_lib-2.0.2.dist-info/WHEEL
mccann_hub_odoo_client_lib-2.0.2.dist-info/top_level.txt
mccann_hub_odoo_client_lib-2.0.2.dist-info/RECORD
