Metadata-Version: 2.4
Name: mccann_hub-odoo_client_lib
Version: 2.0.2
Summary: Extended Odoo Client Library with additional functionality
Home-page: https://github.com/jabez007/odoo-client-lib
Author: Nicolas Vanhoren
Author-email: Jimmy McCann <jabez007@users.noreply.github.com>
License: BSD-2-Clause
Project-URL: Homepage, https://github.com/jabez007/odoo-client-lib
Project-URL: Bug Tracker, https://github.com/jabez007/odoo-client-lib/issues
Project-URL: Original Project, https://github.com/odoo/odoo-client-lib
Keywords: openerp,odoo,library,communication,rpc,xml-rpc,net-rpc,xmlrpc,python,client,lib,web service
Classifier: License :: OSI Approved :: BSD License
Classifier: Programming Language :: Python
Classifier: Programming Language :: Python :: 3
Classifier: Programming Language :: Python :: 3.10
Classifier: Programming Language :: Python :: 3.11
Classifier: Programming Language :: Python :: 3.12
Classifier: Programming Language :: Python :: 3.13
Requires-Python: >=3.10
Requires-Dist: requests
Requires-Dist: asyncio
Dynamic: home-page
Dynamic: requires-python
